{
    "responses": [
        {
            "faceAnnotations": [
                {
                    "boundingPoly": {
                        "vertices": [
                            {},
                            {
                                "x": 156
                            },
                            {
                                "x": 156,
                                "y": 202
                            },
                            {
                                "y": 202
                            }
                        ]
                    },
                    "fdBoundingPoly": {
                        "vertices": [
                            {
                                "x": 10,
                                "y": 36
                            },
                            {
                                "x": 153,
                                "y": 36
                            },
                            {
                                "x": 153,
                                "y": 175
                            },
                            {
                                "x": 10,
                                "y": 175
                            }
                        ]
                    },
                    "landmarks": [
                        {
                            "type": "LEFT_EYE",
                            "position": {
                                "x": 57.68455,
                                "y": 86.90647,
                                "z": -0.00048065186
                            }
                        },
                        {
                            "type": "RIGHT_EYE",
                            "position": {
                                "x": 109.46307,
                                "y": 92.08233,
                                "z": 4.067641
                            }
                        },
                        {
                            "type": "LEFT_OF_LEFT_EYEBROW",
                            "position": {
                                "x": 42.538673,
                                "y": 76.243744,
                                "z": 5.2327876
                            }
                        },
                        {
                            "type": "RIGHT_OF_LEFT_EYEBROW",
                            "position": {
                                "x": 74.085075,
                                "y": 73.26616,
                                "z": -6.038988
                            }
                        },
                        {
                            "type": "LEFT_OF_RIGHT_EYEBROW",
                            "position": {
                                "x": 96.56343,
                                "y": 74.58422,
                                "z": -4.012
                            }
                        },
                        {
                            "type": "RIGHT_OF_RIGHT_EYEBROW",
                            "position": {
                                "x": 128.20695,
                                "y": 83.85164,
                                "z": 12.168648
                            }
                        },
                        {
                            "type": "MIDPOINT_BETWEEN_EYES",
                            "position": {
                                "x": 85.31685,
                                "y": 86.69603,
                                "z": -8.290497
                            }
                        },
                        {
                            "type": "NOSE_TIP",
                            "position": {
                                "x": 83.41458,
                                "y": 111.50682,
                                "z": -28.716698
                            }
                        },
                        {
                            "type": "UPPER_LIP",
                            "position": {
                                "x": 81.75483,
                                "y": 131.68782,
                                "z": -20.846367
                            }
                        },
                        {
                            "type": "LOWER_LIP",
                            "position": {
                                "x": 79.197784,
                                "y": 160.01646,
                                "z": -22.4919
                            }
                        },
                        {
                            "type": "MOUTH_LEFT",
                            "position": {
                                "x": 61.27792,
                                "y": 142.97427,
                                "z": -11.144818
                            }
                        },
                        {
                            "type": "MOUTH_RIGHT",
                            "position": {
                                "x": 99.55222,
                                "y": 148.28682,
                                "z": -8.187712
                            }
                        },
                        {
                            "type": "MOUTH_CENTER",
                            "position": {
                                "x": 81.962944,
                                "y": 142.75865,
                                "z": -19.02466
                            }
                        },
                        {
                            "type": "NOSE_BOTTOM_RIGHT",
                            "position": {
                                "x": 97.91027,
                                "y": 120.42209,
                                "z": -9.489622
                            }
                        },
                        {
                            "type": "NOSE_BOTTOM_LEFT",
                            "position": {
                                "x": 67.50377,
                                "y": 118.0586,
                                "z": -11.861871
                            }
                        },
                        {
                            "type": "NOSE_BOTTOM_CENTER",
                            "position": {
                                "x": 82.752716,
                                "y": 122.18059,
                                "z": -19.111694
                            }
                        },
                        {
                            "type": "LEFT_EYE_TOP_BOUNDARY",
                            "position": {
                                "x": 57.5146,
                                "y": 82.03262,
                                "z": -2.1181164
                            }
                        },
                        {
                            "type": "LEFT_EYE_RIGHT_CORNER",
                            "position": {
                                "x": 68.2646,
                                "y": 87.49136,
                                "z": 0.806139
                            }
                        },
                        {
                            "type": "LEFT_EYE_BOTTOM_BOUNDARY",
                            "position": {
                                "x": 56.98077,
                                "y": 90.68944,
                                "z": -1.3897839
                            }
                        },
                        {
                            "type": "LEFT_EYE_LEFT_CORNER",
                            "position": {
                                "x": 46.23805,
                                "y": 86.46715,
                                "z": 3.7743492
                            }
                        },
                        {
                            "type": "RIGHT_EYE_TOP_BOUNDARY",
                            "position": {
                                "x": 110.58988,
                                "y": 87.36481,
                                "z": 2.0078878
                            }
                        },
                        {
                            "type": "RIGHT_EYE_RIGHT_CORNER",
                            "position": {
                                "x": 120.51089,
                                "y": 93.98842,
                                "z": 9.592882
                            }
                        },
                        {
                            "type": "RIGHT_EYE_BOTTOM_BOUNDARY",
                            "position": {
                                "x": 109.485954,
                                "y": 95.57359,
                                "z": 2.8644571
                            }
                        },
                        {
                            "type": "RIGHT_EYE_LEFT_CORNER",
                            "position": {
                                "x": 98.30255,
                                "y": 90.64549,
                                "z": 3.1650257
                            }
                        },
                        {
                            "type": "LEFT_EYEBROW_UPPER_MIDPOINT",
                            "position": {
                                "x": 58.586205,
                                "y": 69.516205,
                                "z": -2.700221
                            }
                        },
                        {
                            "type": "RIGHT_EYEBROW_UPPER_MIDPOINT",
                            "position": {
                                "x": 112.192566,
                                "y": 74.14306,
                                "z": 1.7208567
                            }
                        },
                        {
                            "type": "LEFT_EAR_TRAGION",
                            "position": {
                                "x": 16.184048,
                                "y": 110.48204,
                                "z": 57.749943
                            }
                        },
                        {
                            "type": "RIGHT_EAR_TRAGION",
                            "position": {
                                "x": 137.7638,
                                "y": 122.232895,
                                "z": 66.99846
                            }
                        },
                        {
                            "type": "FOREHEAD_GLABELLA",
                            "position": {
                                "x": 86.10086,
                                "y": 75.14158,
                                "z": -7.025057
                            }
                        },
                        {
                            "type": "CHIN_GNATHION",
                            "position": {
                                "x": 78.78853,
                                "y": 183.28584,
                                "z": -19.789413
                            }
                        },
                        {
                            "type": "CHIN_LEFT_GONION",
                            "position": {
                                "x": 25.943901,
                                "y": 152.0144,
                                "z": 27.901157
                            }
                        },
                        {
                            "type": "CHIN_RIGHT_GONION",
                            "position": {
                                "x": 127.11906,
                                "y": 163.74245,
                                "z": 35.41632
                            }
                        },
                        {
                            "type": "LEFT_CHEEK_CENTER",
                            "position": {
                                "x": 45.83595,
                                "y": 120.21515,
                                "z": -2.7151651
                            }
                        },
                        {
                            "type": "RIGHT_CHEEK_CENTER",
                            "position": {
                                "x": 116.736496,
                                "y": 127.826035,
                                "z": 2.826787
                            }
                        }
                    ],
                    "rollAngle": 4.0262265,
                    "panAngle": 4.572116,
                    "tiltAngle": 10.327456,
                    "detectionConfidence": 0.5265979,
                    "landmarkingConfidence": 0.6907859,
                    "joyLikelihood": "VERY_UNLIKELY",
                    "sorrowLikelihood": "UNLIKELY",
                    "angerLikelihood": "VERY_UNLIKELY",
                    "surpriseLikelihood": "VERY_UNLIKELY",
                    "underExposedLikelihood": "VERY_UNLIKELY",
                    "blurredLikelihood": "VERY_UNLIKELY",
                    "headwearLikelihood": "VERY_UNLIKELY"
                }
            ]
        }
    ]
}