{
    "responses": [
        {
            "faceAnnotations": [
                {
                    "boundingPoly": {
                        "vertices": [
                            {
                                "x": 9,
                                "y": 1
                            },
                            {
                                "x": 97,
                                "y": 1
                            },
                            {
                                "x": 97,
                                "y": 103
                            },
                            {
                                "x": 9,
                                "y": 103
                            }
                        ]
                    },
                    "fdBoundingPoly": {
                        "vertices": [
                            {
                                "x": 14,
                                "y": 18
                            },
                            {
                                "x": 89,
                                "y": 18
                            },
                            {
                                "x": 89,
                                "y": 92
                            },
                            {
                                "x": 14,
                                "y": 92
                            }
                        ]
                    },
                    "landmarks": [
                        {
                            "type": "LEFT_EYE",
                            "position": {
                                "x": 38.758312,
                                "y": 48.989124,
                                "z": 0.00017526746
                            }
                        },
                        {
                            "type": "RIGHT_EYE",
                            "position": {
                                "x": 65.43877,
                                "y": 47.31419,
                                "z": -1.720056
                            }
                        },
                        {
                            "type": "LEFT_OF_LEFT_EYEBROW",
                            "position": {
                                "x": 29.04815,
                                "y": 43.7514,
                                "z": 2.9532905
                            }
                        },
                        {
                            "type": "RIGHT_OF_LEFT_EYEBROW",
                            "position": {
                                "x": 45.334446,
                                "y": 42.77837,
                                "z": -5.1515923
                            }
                        },
                        {
                            "type": "LEFT_OF_RIGHT_EYEBROW",
                            "position": {
                                "x": 57.683853,
                                "y": 41.933765,
                                "z": -5.95275
                            }
                        },
                        {
                            "type": "RIGHT_OF_RIGHT_EYEBROW",
                            "position": {
                                "x": 74.82309,
                                "y": 40.71155,
                                "z": 0.108739704
                            }
                        },
                        {
                            "type": "MIDPOINT_BETWEEN_EYES",
                            "position": {
                                "x": 51.66731,
                                "y": 47.09172,
                                "z": -6.0125766
                            }
                        },
                        {
                            "type": "NOSE_TIP",
                            "position": {
                                "x": 51.65638,
                                "y": 63.996716,
                                "z": -13.947814
                            }
                        },
                        {
                            "type": "UPPER_LIP",
                            "position": {
                                "x": 52.54582,
                                "y": 71.89456,
                                "z": -8.2812195
                            }
                        },
                        {
                            "type": "LOWER_LIP",
                            "position": {
                                "x": 53.800926,
                                "y": 81.81986,
                                "z": -6.7839017
                            }
                        },
                        {
                            "type": "MOUTH_LEFT",
                            "position": {
                                "x": 40.539703,
                                "y": 74.95436,
                                "z": -0.51677465
                            }
                        },
                        {
                            "type": "MOUTH_RIGHT",
                            "position": {
                                "x": 66.7229,
                                "y": 73.11464,
                                "z": -2.0372665
                            }
                        },
                        {
                            "type": "MOUTH_CENTER",
                            "position": {
                                "x": 53.230587,
                                "y": 76.24685,
                                "z": -6.5520744
                            }
                        },
                        {
                            "type": "NOSE_BOTTOM_RIGHT",
                            "position": {
                                "x": 60.44513,
                                "y": 64.65687,
                                "z": -5.046968
                            }
                        },
                        {
                            "type": "NOSE_BOTTOM_LEFT",
                            "position": {
                                "x": 44.76159,
                                "y": 64.75259,
                                "z": -3.9698017
                            }
                        },
                        {
                            "type": "NOSE_BOTTOM_CENTER",
                            "position": {
                                "x": 52.52802,
                                "y": 67.76963,
                                "z": -8.349823
                            }
                        },
                        {
                            "type": "LEFT_EYE_TOP_BOUNDARY",
                            "position": {
                                "x": 38.288643,
                                "y": 46.57673,
                                "z": -1.3432647
                            }
                        },
                        {
                            "type": "LEFT_EYE_RIGHT_CORNER",
                            "position": {
                                "x": 43.892178,
                                "y": 49.06583,
                                "z": -0.3695209
                            }
                        },
                        {
                            "type": "LEFT_EYE_BOTTOM_BOUNDARY",
                            "position": {
                                "x": 38.81911,
                                "y": 50.886215,
                                "z": -0.29381496
                            }
                        },
                        {
                            "type": "LEFT_EYE_LEFT_CORNER",
                            "position": {
                                "x": 33.75717,
                                "y": 49.97168,
                                "z": 2.6032488
                            }
                        },
                        {
                            "type": "RIGHT_EYE_TOP_BOUNDARY",
                            "position": {
                                "x": 65.482704,
                                "y": 44.747204,
                                "z": -3.0828393
                            }
                        },
                        {
                            "type": "RIGHT_EYE_RIGHT_CORNER",
                            "position": {
                                "x": 70.68809,
                                "y": 47.543118,
                                "z": 0.19201249
                            }
                        },
                        {
                            "type": "RIGHT_EYE_BOTTOM_BOUNDARY",
                            "position": {
                                "x": 65.65711,
                                "y": 49.248207,
                                "z": -2.0545437
                            }
                        },
                        {
                            "type": "RIGHT_EYE_LEFT_CORNER",
                            "position": {
                                "x": 60.250156,
                                "y": 48.166245,
                                "z": -1.40011
                            }
                        },
                        {
                            "type": "LEFT_EYEBROW_UPPER_MIDPOINT",
                            "position": {
                                "x": 37.002373,
                                "y": 40.83387,
                                "z": -2.5666242
                            }
                        },
                        {
                            "type": "RIGHT_EYEBROW_UPPER_MIDPOINT",
                            "position": {
                                "x": 66.023926,
                                "y": 38.74604,
                                "z": -4.4005575
                            }
                        },
                        {
                            "type": "LEFT_EAR_TRAGION",
                            "position": {
                                "x": 23.69209,
                                "y": 61.82185,
                                "z": 31.83645
                            }
                        },
                        {
                            "type": "RIGHT_EAR_TRAGION",
                            "position": {
                                "x": 84.69981,
                                "y": 58.900692,
                                "z": 27.986294
                            }
                        },
                        {
                            "type": "FOREHEAD_GLABELLA",
                            "position": {
                                "x": 51.221638,
                                "y": 41.48037,
                                "z": -6.3602953
                            }
                        },
                        {
                            "type": "CHIN_GNATHION",
                            "position": {
                                "x": 55.111675,
                                "y": 94.01215,
                                "z": -3.5370014
                            }
                        },
                        {
                            "type": "CHIN_LEFT_GONION",
                            "position": {
                                "x": 30.01014,
                                "y": 80.25058,
                                "z": 20.738253
                            }
                        },
                        {
                            "type": "CHIN_RIGHT_GONION",
                            "position": {
                                "x": 79.62603,
                                "y": 78.00541,
                                "z": 17.604908
                            }
                        },
                        {
                            "type": "LEFT_CHEEK_CENTER",
                            "position": {
                                "x": 34.4699,
                                "y": 66.50101,
                                "z": 2.3669748
                            }
                        },
                        {
                            "type": "RIGHT_CHEEK_CENTER",
                            "position": {
                                "x": 71.869576,
                                "y": 64.00626,
                                "z": -0.018162519
                            }
                        }
                    ],
                    "rollAngle": -3.1766484,
                    "panAngle": -3.7588758,
                    "tiltAngle": 0.43822297,
                    "detectionConfidence": 0.87635446,
                    "landmarkingConfidence": 0.637814,
                    "joyLikelihood": "VERY_LIKELY",
                    "sorrowLikelihood": "VERY_UNLIKELY",
                    "angerLikelihood": "VERY_UNLIKELY",
                    "surpriseLikelihood": "VERY_UNLIKELY",
                    "underExposedLikelihood": "VERY_UNLIKELY",
                    "blurredLikelihood": "VERY_UNLIKELY",
                    "headwearLikelihood": "VERY_UNLIKELY"
                }
            ]
        }
    ]
}