{
    "responses": [
        {
            "faceAnnotations": [
                {
                    "boundingPoly": {
                        "vertices": [
                            {},
                            {
                                "x": 189
                            },
                            {
                                "x": 189,
                                "y": 238
                            },
                            {
                                "y": 238
                            }
                        ]
                    },
                    "fdBoundingPoly": {
                        "vertices": [
                            {
                                "x": 14,
                                "y": 38
                            },
                            {
                                "x": 188,
                                "y": 38
                            },
                            {
                                "x": 188,
                                "y": 217
                            },
                            {
                                "x": 14,
                                "y": 217
                            }
                        ]
                    },
                    "landmarks": [
                        {
                            "type": "LEFT_EYE",
                            "position": {
                                "x": 78.36054,
                                "y": 103.60778,
                                "z": 0.00044250488
                            }
                        },
                        {
                            "type": "RIGHT_EYE",
                            "position": {
                                "x": 139.17366,
                                "y": 111.55017,
                                "z": 6.6426353
                            }
                        },
                        {
                            "type": "LEFT_OF_LEFT_EYEBROW",
                            "position": {
                                "x": 57.533375,
                                "y": 89.62822,
                                "z": 4.59956
                            }
                        },
                        {
                            "type": "RIGHT_OF_LEFT_EYEBROW",
                            "position": {
                                "x": 97.22894,
                                "y": 90.00151,
                                "z": -8.062855
                            }
                        },
                        {
                            "type": "LEFT_OF_RIGHT_EYEBROW",
                            "position": {
                                "x": 124.70732,
                                "y": 93.732544,
                                "z": -4.996541
                            }
                        },
                        {
                            "type": "RIGHT_OF_RIGHT_EYEBROW",
                            "position": {
                                "x": 162.45468,
                                "y": 101.85185,
                                "z": 16.158257
                            }
                        },
                        {
                            "type": "MIDPOINT_BETWEEN_EYES",
                            "position": {
                                "x": 110.59106,
                                "y": 104.67113,
                                "z": -9.085479
                            }
                        },
                        {
                            "type": "NOSE_TIP",
                            "position": {
                                "x": 109.27348,
                                "y": 136.95226,
                                "z": -31.369722
                            }
                        },
                        {
                            "type": "UPPER_LIP",
                            "position": {
                                "x": 103.42139,
                                "y": 164.04477,
                                "z": -21.150146
                            }
                        },
                        {
                            "type": "LOWER_LIP",
                            "position": {
                                "x": 99.90446,
                                "y": 186.80914,
                                "z": -19.790215
                            }
                        },
                        {
                            "type": "MOUTH_LEFT",
                            "position": {
                                "x": 70.29534,
                                "y": 167.91312,
                                "z": -8.06989
                            }
                        },
                        {
                            "type": "MOUTH_RIGHT",
                            "position": {
                                "x": 128.2788,
                                "y": 178.6075,
                                "z": -2.922917
                            }
                        },
                        {
                            "type": "MOUTH_CENTER",
                            "position": {
                                "x": 100.81907,
                                "y": 174.41539,
                                "z": -17.960342
                            }
                        },
                        {
                            "type": "NOSE_BOTTOM_RIGHT",
                            "position": {
                                "x": 123.754616,
                                "y": 150.14738,
                                "z": -8.285181
                            }
                        },
                        {
                            "type": "NOSE_BOTTOM_LEFT",
                            "position": {
                                "x": 86.752266,
                                "y": 141.7525,
                                "z": -11.346251
                            }
                        },
                        {
                            "type": "NOSE_BOTTOM_CENTER",
                            "position": {
                                "x": 105.80612,
                                "y": 149.68626,
                                "z": -19.401737
                            }
                        },
                        {
                            "type": "LEFT_EYE_TOP_BOUNDARY",
                            "position": {
                                "x": 78.13881,
                                "y": 97.58032,
                                "z": -2.8921995
                            }
                        },
                        {
                            "type": "LEFT_EYE_RIGHT_CORNER",
                            "position": {
                                "x": 90.55285,
                                "y": 105.51898,
                                "z": 1.215117
                            }
                        },
                        {
                            "type": "LEFT_EYE_BOTTOM_BOUNDARY",
                            "position": {
                                "x": 77.493454,
                                "y": 107.936966,
                                "z": -1.2985802
                            }
                        },
                        {
                            "type": "LEFT_EYE_LEFT_CORNER",
                            "position": {
                                "x": 65.617,
                                "y": 103.76297,
                                "z": 4.0726156
                            }
                        },
                        {
                            "type": "RIGHT_EYE_TOP_BOUNDARY",
                            "position": {
                                "x": 140.87111,
                                "y": 105.64719,
                                "z": 3.9617448
                            }
                        },
                        {
                            "type": "RIGHT_EYE_RIGHT_CORNER",
                            "position": {
                                "x": 151.57594,
                                "y": 114.42274,
                                "z": 13.525546
                            }
                        },
                        {
                            "type": "RIGHT_EYE_BOTTOM_BOUNDARY",
                            "position": {
                                "x": 138.91653,
                                "y": 115.925674,
                                "z": 5.4603963
                            }
                        },
                        {
                            "type": "RIGHT_EYE_LEFT_CORNER",
                            "position": {
                                "x": 126.06138,
                                "y": 110.38176,
                                "z": 5.1185575
                            }
                        },
                        {
                            "type": "LEFT_EYEBROW_UPPER_MIDPOINT",
                            "position": {
                                "x": 78.465904,
                                "y": 83.17522,
                                "z": -4.669548
                            }
                        },
                        {
                            "type": "RIGHT_EYEBROW_UPPER_MIDPOINT",
                            "position": {
                                "x": 144.843,
                                "y": 91.323654,
                                "z": 2.6206484
                            }
                        },
                        {
                            "type": "LEFT_EAR_TRAGION",
                            "position": {
                                "x": 29.887207,
                                "y": 125.958786,
                                "z": 69.57426
                            }
                        },
                        {
                            "type": "RIGHT_EAR_TRAGION",
                            "position": {
                                "x": 165.78688,
                                "y": 146.99591,
                                "z": 84.110565
                            }
                        },
                        {
                            "type": "FOREHEAD_GLABELLA",
                            "position": {
                                "x": 112.19306,
                                "y": 91.670784,
                                "z": -8.567556
                            }
                        },
                        {
                            "type": "CHIN_GNATHION",
                            "position": {
                                "x": 93.216675,
                                "y": 221.4896,
                                "z": -15.813185
                            }
                        },
                        {
                            "type": "CHIN_LEFT_GONION",
                            "position": {
                                "x": 33.01672,
                                "y": 180.37238,
                                "z": 37.361717
                            }
                        },
                        {
                            "type": "CHIN_RIGHT_GONION",
                            "position": {
                                "x": 150.4911,
                                "y": 196.0408,
                                "z": 49.94146
                            }
                        },
                        {
                            "type": "LEFT_CHEEK_CENTER",
                            "position": {
                                "x": 59.591507,
                                "y": 143.84045,
                                "z": -0.91677856
                            }
                        },
                        {
                            "type": "RIGHT_CHEEK_CENTER",
                            "position": {
                                "x": 145.75374,
                                "y": 155.57657,
                                "z": 8.1896515
                            }
                        }
                    ],
                    "rollAngle": 7.1673703,
                    "panAngle": 6.0595503,
                    "tiltAngle": 6.6409,
                    "detectionConfidence": 0.6876091,
                    "landmarkingConfidence": 0.78540474,
                    "joyLikelihood": "POSSIBLE",
                    "sorrowLikelihood": "VERY_UNLIKELY",
                    "angerLikelihood": "VERY_UNLIKELY",
                    "surpriseLikelihood": "VERY_UNLIKELY",
                    "underExposedLikelihood": "VERY_UNLIKELY",
                    "blurredLikelihood": "VERY_UNLIKELY",
                    "headwearLikelihood": "VERY_UNLIKELY"
                }
            ]
        }
    ]
}